SMILESTracer/__init__.py
SMILESTracer/labling_rxn.py
SMILESTracer/rxn_smiles_preprocess.py
SMILESTracer/smarts_preprocess.py
SMILESTracer-0.1.dist-info/LICENSE
SMILESTracer-0.1.dist-info/METADATA
SMILESTracer-0.1.dist-info/WHEEL
SMILESTracer-0.1.dist-info/entry_points.txt
SMILESTracer-0.1.dist-info/top_level.txt
SMILESTracer-0.1.dist-info/RECORD
