Metadata-Version: 2.1
Name: SMILESTracer
Version: 0.1
Summary: Labling reaction SMILES with atom-mapped SMARTS and reaction SMILES
Home-page: https://github.com/DMSO0408/SMILESTracer.git
Author: jnliu
Author-email: 2100011879@stu.pku.edu.cn
Classifier: Programming Language :: Python :: 3
Classifier: License :: OSI Approved :: MIT License
Classifier: Operating System :: OS Independent
License-File: LICENSE
